klarity_connector/__init__.py
klarity_connector/connector.py
klarity_connector-0.1.5.dist-info/LICENSE.md
klarity_connector-0.1.5.dist-info/METADATA
klarity_connector-0.1.5.dist-info/WHEEL
klarity_connector-0.1.5.dist-info/top_level.txt
klarity_connector-0.1.5.dist-info/RECORD
