Metadata-Version: 2.1
Name: klarity-connector
Version: 0.1.5
Summary: Python connector to GraphQL API of Klarity
Home-page: https://github.com/Kacperek0/klarity-connector
Author: Kacper Szczepanek
Author-email: pypi@szczepanek.dev
License: MIT
Classifier: Intended Audience :: Developers
Classifier: License :: OSI Approved :: MIT License
Classifier: Programming Language :: Python
Classifier: Programming Language :: Python :: 3
Classifier: Programming Language :: Python :: 3.6
Classifier: Programming Language :: Python :: 3.7
Classifier: Programming Language :: Python :: 3.8
Classifier: Programming Language :: Python :: 3.9
Classifier: Programming Language :: Python :: 3.10
Classifier: Programming Language :: Python :: 3.11
Classifier: Topic :: Software Development :: Libraries
Classifier: Operating System :: OS Independent
License-File: LICENSE.md
Requires-Dist: requests
